ascl_net_scraper/__init__.py
ascl_net_scraper/__main__.py
ascl_net_scraper/lib.py
ascl_net_scraper/py.typed
ascl_net_scraper-0.3.7.dist-info/LICENSE
ascl_net_scraper-0.3.7.dist-info/WHEEL
ascl_net_scraper-0.3.7.dist-info/METADATA
ascl_net_scraper-0.3.7.dist-info/RECORD
