Metadata-Version: 2.1
Name: ascl-net-scraper
Version: 0.3.7
Summary: Scrapes the data from https://ascl.net
Home-page: https://github.com/charmoniumQ/ascl_net_scraper
License: MIT
Keywords: webscraper
Author: Samuel Grayson
Author-email: sam+dev@samgrayson.me
Requires-Python: >=3.8,<4.0
Classifier: Development Status :: 4 - Beta
Classifier: Intended Audience :: Science/Research
Classifier: License :: OSI Approved :: MIT License
Classifier: Natural Language :: English
Classifier: Operating System :: OS Independent
Classifier: Programming Language :: Python :: 3
Classifier: Programming Language :: Python :: 3.10
Classifier: Programming Language :: Python :: 3.8
Classifier: Programming Language :: Python :: 3.9
Classifier: Topic :: Scientific/Engineering
Classifier: Typing :: Typed
Requires-Dist: bs4 (>=0.0.1,<0.0.2)
Requires-Dist: charmonium.cache (>=1.2.6,<2.0.0)
Requires-Dist: html5lib (>=1.1,<2.0)
Requires-Dist: requests (>=2.27.1,<3.0.0)
Project-URL: Repository, https://github.com/charmoniumQ/ascl_net_scraper
